epanns_inference/__init__.py
epanns_inference/models/__init__.py
epanns_inference/models/models.py
epanns_inference/models/utils.py
epanns_inference-0.1.1.dist-info/LICENSE
epanns_inference-0.1.1.dist-info/METADATA
epanns_inference-0.1.1.dist-info/WHEEL
epanns_inference-0.1.1.dist-info/top_level.txt
epanns_inference-0.1.1.dist-info/RECORD
